as_project/__init__.py
as_project/alphabet_soup.py
as_project/test/__init__.py
as_project/test/soup_test.py
as_project/test/test.out
as_project/test/test1.txt
as_project/test/test2.txt
as_project/test/test3.txt
as_project/test/test4.txt
as_project/test/test5.txt
as_project-0.1.3.data/scripts/given.py
as_project-0.1.3.data/scripts/main.py
as_project-0.1.3.dist-info/METADATA
as_project-0.1.3.dist-info/WHEEL
as_project-0.1.3.dist-info/top_level.txt
as_project-0.1.3.dist-info/RECORD
