Metadata-Version: 2.1
Name: as-project
Version: 0.1.3
Summary: Enlighten coding project--alphabet soup
Home-page: UNKNOWN
Author: Charlene DiMiceli
Author-email: cdimicel@umd.edu
License: UNKNOWN
Platform: UNKNOWN
Requires-Dist: numpy
